stringtoolsfpat/__init__.py
tests/__init__.py
tests/test_stringtools.py
stringtoolsfpat-0.0.70.dist-info/METADATA
stringtoolsfpat-0.0.70.dist-info/WHEEL
stringtoolsfpat-0.0.70.dist-info/top_level.txt
stringtoolsfpat-0.0.70.dist-info/RECORD
